ShiftReg4bit/src/ShiftReg4bit.v
//4-Bit Shift Register
module shift_reg_4bit (
    input  wire       clk,    // Clock
    input  wire       rst,    // Synchronous reset
    input  wire       din,    // Serial data input
    output reg  [3:0] q       // 4-bit shift register output
);

    always @(posedge clk) begin
        if (rst) begin
            q <= 4'b0000;              // Clear on reset
        end else begin
            q <= {q[2:0], din};        // Shift left, insert din
        end
    end

endmodule

ShiftReg4bit/src/ShiftReg4bit_tb.v
//ShiftReg Testbench
`timescale 1ns/1ps

module shift_reg_4bit_tb;

    reg clk;
    reg rst;
    reg din;
    wire [3:0] q;

    // Instantiate DUT (Device Under Test)
    shift_reg_4bit uut (
        .clk(clk),
        .rst(rst),
        .din(din),
        .q(q)
    );
initial begin
    $dumpfile("shift_reg_4bit.vcd");  // waveform dump file
    $dumpvars(0, shift_reg_4bit_tb); // dump everything in tb
end

    // Clock generation: 10ns period
    always #5 clk = ~clk;

    initial begin
        // Initialize signals
        clk = 0;
        rst = 1;
        din = 0;

        // Apply reset for 2 cycles
        #20 rst = 0;

        // Feed in data bits
        din = 1; #10;   // shift in 1
        din = 0; #10;   // shift in 0
        din = 1; #10;   // shift in 1
        din = 1; #10;   // shift in 1
        din = 0; #10;   // shift in 0
        din = 1; #10;   // shift in 1

        // Hold for a while
        #50;

        $finish;
    end

    // Monitor values
    initial begin
        $monitor("Time=%0t | rst=%b | din=%b | q=%b",
                  $time, rst, din, q);
    end

endmodule

ShiftReg4bit/sim/shift_reg_4bit.vcd
$date
	Mon Sep 15 23:23:51 2025
$end
$version
	Icarus Verilog
$end
$timescale
	1ps
$end
$scope module shift_reg_4bit_tb $end
$var wire 4 ! q [3:0] $end
$var reg 1 " clk $end
$var reg 1 # din $end
$var reg 1 $ rst $end
$scope module uut $end
$var wire 1 " clk $end
$var wire 1 # din $end
$var wire 1 $ rst $end
$var reg 4 % q [3:0] $end
$upscope $end
$upscope $end
$enddefinitions $end
$comment Show the parameter values. $end
$dumpall
$end
#0
$dumpvars
bx %
1$
0#
0"
bx !
$end
#5000
b0 !
b0 %
1"
#10000
0"
#15000
1"
#20000
0"
1#
0$
#25000
b1 !
b1 %
1"
#30000
0"
0#
#35000
b10 !
b10 %
1"
#40000
0"
1#
#45000
b101 !
b101 %
1"
#50000
0"
#55000
b1011 !
b1011 %
1"
#60000
0"
0#
#65000
b110 !
b110 %
1"
#70000
0"
1#
#75000
b1101 !
b1101 %
1"
#80000
0"
#85000
b1011 !
b1011 %
1"
#90000
0"
#95000
b111 !
b111 %
1"
#100000
0"
#105000
b1111 !
b1111 %
1"
